LICENSE
MANIFEST.in
README.rst
requirements.txt
setup.py
persair/__init__.py
persair/__main__.py
persair/persair.py
persair.egg-info/PKG-INFO
persair.egg-info/SOURCES.txt
persair.egg-info/dependency_links.txt
persair.egg-info/entry_points.txt
persair.egg-info/not-zip-safe
persair.egg-info/requires.txt
persair.egg-info/top_level.txt
persair/config/__init__.py
persair/config/settings.py
persair/models/sensorModel.py