Metadata-Version: 2.1
Name: persair
Version: 2.2.22
Summary: A mongodb aware purple air client
Home-page: https://github.com/FNNDSC/persair
Author: FNNDSC
Author-email: dev@babymri.org
License: MIT
License-File: LICENSE
Requires-Dist: aiohttp
Requires-Dist: pudb
Requires-Dist: ipython
Requires-Dist: pytest
Requires-Dist: motor
Requires-Dist: dnspython
Requires-Dist: loguru
Requires-Dist: pfmisc
Requires-Dist: build
Requires-Dist: pydantic>=2.3.0
Requires-Dist: pydantic_settings
Requires-Dist: numpy
Requires-Dist: scipy
Requires-Dist: webob
Requires-Dist: print-color
Requires-Dist: matplotlib
